soyutnet/__init__.py
soyutnet/constants.py
soyutnet/observer.py
soyutnet/place.py
soyutnet/pt_common.py
soyutnet/registry.py
soyutnet/token.py
soyutnet/transition.py
soyutnet/validate.py
soyutnet-0.4.0.dist-info/METADATA
soyutnet-0.4.0.dist-info/WHEEL
soyutnet-0.4.0.dist-info/licenses/LICENSE.md
soyutnet-0.4.0.dist-info/RECORD
