Metadata-Version: 2.3
Name: soyutnet
Version: 0.4.0
Summary: Place/transition net (petri net) simulator that uses asyncio utilities as backend
Project-URL: Homepage, https://github.com/dmrokan/soyutnet
Project-URL: Documentation, https://github.com/dmrokan/soyutnet
Project-URL: Repository, https://github.com/dmrokan/soyutnet
Project-URL: Bug Tracker, https://github.com/dmrokan/soyutnet/issues
Project-URL: Changelog, https://github.com/dmrokan/soyutnet/blob/main/CHANGELOG.md
Author-email: Okan Demir <okndemir@gmail.com>
Maintainer-email: Okan Demir <okndemir@gmail.com>
License: Copyright (c) 2024 Okan Demir
Keywords: discrete-event-systems,petri-net,pt-net,simulator
Classifier: License :: OSI Approved :: MIT License
Classifier: Operating System :: OS Independent
Classifier: Programming Language :: Python :: 3
Requires-Python: >=3.10
Requires-Dist: typing-extensions>=4.12.2
Provides-Extra: dev
Requires-Dist: black>=24.10.0; extra == 'dev'
Requires-Dist: mypy>=1.13.0; extra == 'dev'
Requires-Dist: pytest-asyncio; extra == 'dev'
Requires-Dist: pytest-cov; extra == 'dev'
Requires-Dist: pytest-randomly; extra == 'dev'
Requires-Dist: pytest>=8.3.3; extra == 'dev'
Provides-Extra: doc
Requires-Dist: sphinx>=8.1.3; extra == 'doc'
Provides-Extra: test
Requires-Dist: pytest-asyncio; extra == 'test'
Requires-Dist: pytest-cov; extra == 'test'
Requires-Dist: pytest-randomly; extra == 'test'
Requires-Dist: pytest>=8.3.3; extra == 'test'
